MANIFEST.in
README.rst
setup.cfg
setup.py
lazy/__init__.py
lazy/_thunk.c
lazy/_undefined.c
lazy/bytecode.py
lazy/runtime.py
lazy/tree.py
lazy/utils.py
lazy/data/__init__.py
lazy/data/empty.py
lazy/data/list_.py
lazy/data/tests/__init__.py
lazy/data/tests/test_list.py
lazy/include/__init__.py
lazy/include/lazy.h
lazy/include/__pycache__/__init__.cpython-34.pyc
lazy/tests/__init__.py
lazy/tests/test_lazy_function.py
lazy/tests/test_strict.py
lazy/tests/test_thunk.py
lazy/tests/test_tree.py
lazy/tests/test_undefined.py
lazy/tests/test_utils.py
lazy_python.egg-info/PKG-INFO
lazy_python.egg-info/SOURCES.txt
lazy_python.egg-info/dependency_links.txt
lazy_python.egg-info/requires.txt
lazy_python.egg-info/top_level.txt