Metadata-Version: 1.1
Name: lazy-python
Version: 0.2.1
Summary: Lazy evaluation for python 3
Home-page: https://github.com/llllllllll/lazy_python
Author: Joe Jevnik
Author-email: joejev@gmail.com
License: GPL-2
Platform: UNKNOWN
Classifier: Development Status :: 3 - Alpha
Classifier: License :: OSI Approved :: GNU General Public License v2 (GPLv2)
Classifier: Natural Language :: English
Classifier: Programming Language :: Python :: 3 :: Only
Classifier: Programming Language :: Python :: Implementation :: CPython
Classifier: Operating System :: POSIX
Classifier: Topic :: Software Development :: Pre-processors
